<?xml version="1.0" encoding="utf-8" ?>
<dwsync>
<file name="alberca-incanto-residencial.jpg" server="ftp.bosquereal.com.mx" local="133136182741246039" remote="133166373000000000" Dst="1" />
<file name="cine-incanto-residencial.jpg" server="ftp.bosquereal.com.mx" local="133136183762333781" remote="133166373000000000" Dst="1" />
<file name="gym-incanto-residencial.jpg" server="ftp.bosquereal.com.mx" local="133136183835203466" remote="133166373000000000" Dst="1" />
<file name="cigar-room-incanto-residencial.jpg" server="ftp.bosquereal.com.mx" local="133136183672517445" remote="133166373000000000" Dst="1" />
<file name="business-center-incanto-residencial.jpg" server="ftp.bosquereal.com.mx" local="133136183552991832" remote="133166373000000000" Dst="1" />
<file name="incanto-drone-2.jpg" server="ftp.bosquereal.com.mx" local="133136151230517950" remote="133166373000000000" Dst="1" />
<file name="incanto-front.jpg" server="ftp.bosquereal.com.mx" local="133136150971503027" remote="133166373000000000" Dst="1" />
<file name="incanto-drone.jpg" server="ftp.bosquereal.com.mx" local="133136151104016133" remote="133166373000000000" Dst="1" />
<file name="juniors-cliub-incanto-residencial.jpg" server="ftp.bosquereal.com.mx" local="133136185234216965" remote="133166373000000000" Dst="1" />
<file name="kids-club-incanto-residencial.jpg" server="ftp.bosquereal.com.mx" local="133136182543361830" remote="133166373000000000" Dst="1" />
<file name="terraza-incanto-residencial.jpg" server="ftp.bosquereal.com.mx" local="133136185714337271" remote="133166373000000000" Dst="1" />
<file name="salon-eventos-incanto-residencial.jpg" server="ftp.bosquereal.com.mx" local="133136185517532243" remote="133166373000000000" Dst="1" />
<file name="tipo-a-torre-1.png" server="ftp.bosquereal.com.mx" local="133136202265661134" remote="133166373000000000" Dst="1" />
<file name="tipo-b-torre-1.png" server="ftp.bosquereal.com.mx" local="133136201852091049" remote="133166373000000000" Dst="1" />
<file name="tipo-c-torre2.png" server="ftp.bosquereal.com.mx" local="133136201398386625" remote="133166373000000000" Dst="1" />
<file name="banner-incanto-residencial.jpg" server="ftp.bosquereal.com.mx" local="133168563980000000" remote="133168350000000000" Dst="1" />
<file name="incanto-movil.jpg" server="ftp.bosquereal.com.mx" local="133168536580000000" remote="133168322400000000" Dst="1" />
<file name="incanto-residencial-logo.png" server="ftp.bosquereal.com.mx" local="133141278053051494" remote="133166373000000000" Dst="1" />
<file name="incanto-lotes-1.jpg" server="ftp.bosquereal.com.mx" local="133148249208786515" remote="133166373000000000" Dst="1" />
<file name="incanto-residencial-2.png" server="ftp.bosquereal.com.mx" local="133178642499275008" remote="133179367200000000" Dst="1" />
<file name="incanto-residencial-departamentos.jpg" server="ftp.bosquereal.com.mx" local="133184173200000000" remote="133185400800000000" Dst="1" />
<file name="tipo-a-incanto-residencial-gr.png" server="ftp.bosquereal.com.mx" local="133196687123646639" remote="133196825400000000" Dst="1" />
<file name="tipo-b-torre-1-incanto-residencial-gr.png" server="ftp.bosquereal.com.mx" local="133196688689047631" remote="133196825400000000" Dst="1" />
<file name="tipo-c-torre-2-incanto-residencial-gr.png" server="ftp.bosquereal.com.mx" local="133196689238353124" remote="133196825400000000" Dst="1" />
<file name="cta-incanto-residencial.jpg" server="ftp.bosquereal.com.mx" local="133205244493262142" remote="133208929200000000" Dst="1" />
</dwsync>