<?xml version="1.0" encoding="utf-8" ?>
<dwsync>
<file name="blue.jpg" server="ftp.bosquereal.com.mx" local="133215005016446965" remote="133215805200000000" Dst="1" />
<file name="boehm.jpg" server="ftp.bosquereal.com.mx" local="133215005016466912" remote="133215805200000000" Dst="1" />
<file name="designo.jpg" server="ftp.bosquereal.com.mx" local="133215005016476889" remote="133215805200000000" Dst="1" />
<file name="incanto.jpg" server="ftp.bosquereal.com.mx" local="133215005016505208" remote="133215805200000000" Dst="1" />
<file name="ivy.jpg" server="ftp.bosquereal.com.mx" local="133215005016525178" remote="133215805200000000" Dst="1" />
<file name="la-vista.jpg" server="ftp.bosquereal.com.mx" local="133215005016525178" remote="133215805200000000" Dst="1" />
<file name="life.jpg" server="ftp.bosquereal.com.mx" local="133215005016535152" remote="133215805200000000" Dst="1" />
<file name="nativ.jpg" server="ftp.bosquereal.com.mx" local="133215005016545127" remote="133215805200000000" Dst="1" />
<file name="nox.jpg" server="ftp.bosquereal.com.mx" local="133215005016565074" remote="133215805200000000" Dst="1" />
<file name="skyview.jpg" server="ftp.bosquereal.com.mx" local="133215005016595000" remote="133215805200000000" Dst="1" />
<file name="residence.jpg" server="ftp.bosquereal.com.mx" local="133215005016585023" remote="133215805200000000" Dst="1" />
<file name="reserva.jpg" server="ftp.bosquereal.com.mx" local="133215005016565074" remote="133215805200000000" Dst="1" />
<file name="ekato.jpg" server="ftp.bosquereal.com.mx" local="133215005016486862" remote="133215805200000000" Dst="1" />
<file name="incanto-residencial.jpg" server="ftp.bosquereal.com.mx" local="133215005016505208" remote="133215805200000000" Dst="1" />
</dwsync>